falconpydev/README.md
falconpydev/__init__.py
falconpydev/_version.py
falconpydev/alerts.py
falconpydev/api_integrations.py
falconpydev/aspm.py
falconpydev/cao_hunting.py
falconpydev/case_management.py
falconpydev/certificate_based_exclusions.py
falconpydev/cloud_aws_registration.py
falconpydev/cloud_azure_registration.py
falconpydev/cloud_connect_aws.py
falconpydev/cloud_google_cloud_registration.py
falconpydev/cloud_oci_registration.py
falconpydev/cloud_policies.py
falconpydev/cloud_security.py
falconpydev/cloud_security_assets.py
falconpydev/cloud_security_compliance.py
falconpydev/cloud_security_detections.py
falconpydev/cloud_snapshots.py
falconpydev/configuration_assessment.py
falconpydev/configuration_assessment_evaluation_logic.py
falconpydev/container_alerts.py
falconpydev/container_detections.py
falconpydev/container_image_compliance.py
falconpydev/container_images.py
falconpydev/container_packages.py
falconpydev/container_vulnerabilities.py
falconpydev/content_update_policies.py
falconpydev/correlation_rules.py
falconpydev/correlation_rules_admin.py
falconpydev/cspm_registration.py
falconpydev/custom_ioa.py
falconpydev/custom_storage.py
falconpydev/d4c_registration.py
falconpydev/data_protection_configuration.py
falconpydev/debug.py
falconpydev/delivery_settings.py
falconpydev/deployments.py
falconpydev/detects.py
falconpydev/device_content.py
falconpydev/device_control_policies.py
falconpydev/discover.py
falconpydev/downloads.py
falconpydev/drift_indicators.py
falconpydev/event_streams.py
falconpydev/exposure_management.py
falconpydev/faas_execution.py
falconpydev/falcon_complete_dashboard.py
falconpydev/falcon_container.py
falconpydev/falconx_sandbox.py
falconpydev/fdr.py
falconpydev/filevantage.py
falconpydev/firewall_management.py
falconpydev/firewall_policies.py
falconpydev/foundry_logscale.py
falconpydev/host_group.py
falconpydev/host_migration.py
falconpydev/hosts.py
falconpydev/identity_protection.py
falconpydev/image_assessment_policies.py
crowdstrike_falconpy_dev-1.6.0.dist-info/METADATA
crowdstrike_falconpy_dev-1.6.0.dist-info/WHEEL
crowdstrike_falconpy_dev-1.6.0.dist-info/licenses/AUTHORS.md
crowdstrike_falconpy_dev-1.6.0.dist-info/licenses/LICENSE
crowdstrike_falconpy_dev-1.6.0.dist-info/RECORD
