Metadata-Version: 2.4
Name: crowdstrike-falconpy-dev
Version: 1.6.0
Summary: The CrowdStrike Falcon SDK for Python
Project-URL: Documentation, https://www.falconpy.io
Project-URL: Homepage, https://github.com/CrowdStrike/falconpy
Project-URL: Source, https://github.com/CrowdStrike/falconpy/tree/main/src/falconpydev
Project-URL: Tracker, https://github.com/CrowdStrike/falconpy/issues
Author-email: CrowdStrike <falconpy@crowdstrike.com>
Maintainer-email: Joshua Hiller <falconpy@crowdstrike.com>
License: This is free and unencumbered software released into the public domain.
License-File: AUTHORS.md
License-File: LICENSE
Keywords: api,crowdstrike,crowdstrike-falcon,devsecops,falcon,oauth2,sdk
Classifier: Development Status :: 5 - Production/Stable
Classifier: Framework :: Flake8
Classifier: Intended Audience :: Developers
Classifier: License :: OSI Approved :: The Unlicense (Unlicense)
Classifier: Natural Language :: English
Classifier: Operating System :: MacOS
Classifier: Operating System :: Microsoft :: Windows
Classifier: Operating System :: OS Independent
Classifier: Operating System :: POSIX
Classifier: Operating System :: POSIX :: Linux
Classifier: Operating System :: Unix
Classifier: Programming Language :: Python
Classifier: Programming Language :: Python :: 3
Classifier: Programming Language :: Python :: 3.8
Classifier: Programming Language :: Python :: 3.9
Classifier: Programming Language :: Python :: 3.10
Classifier: Programming Language :: Python :: 3.11
Classifier: Programming Language :: Python :: 3.12
Classifier: Programming Language :: Python :: 3.13
Classifier: Programming Language :: Python :: 3.14
Classifier: Topic :: Security
Classifier: Topic :: Software Development :: Libraries :: Python Modules
Classifier: Topic :: System :: Systems Administration
Classifier: Topic :: Utilities
Requires-Python: >=3.8
Requires-Dist: requests
Requires-Dist: urllib3
Provides-Extra: dev
Requires-Dist: bandit; extra == 'dev'
Requires-Dist: coverage; extra == 'dev'
Requires-Dist: flake8; extra == 'dev'
Requires-Dist: pydocstyle; extra == 'dev'
Requires-Dist: pylint; extra == 'dev'
Requires-Dist: pytest; extra == 'dev'
Requires-Dist: pytest-cov; extra == 'dev'
